drones/__init__.py
drones/admin.py
drones/apps.py
drones/forms.py
drones/models.py
drones/tests.py
drones/urls.py
drones/views.py
drones/migrations/0001_initial.py
drones/migrations/0002_standardoperatingprocedure.py
drones/migrations/0003_sopdocument_standardoperatingprocedure_slug_and_more.py
drones/migrations/0004_generaldocument.py
drones/migrations/0005_alter_generaldocument_category.py
drones/migrations/0006_delete_standardoperatingprocedure.py
drones/migrations/0007_equipment.py
drones/migrations/__init__.py
drones/migrations/__pycache__/0001_initial.cpython-313.pyc
drones/migrations/__pycache__/0002_standardoperatingprocedure.cpython-313.pyc
drones/migrations/__pycache__/0003_sopdocument_standardoperatingprocedure_slug_and_more.cpython-313.pyc
drones/migrations/__pycache__/0004_generaldocument.cpython-313.pyc
drones/migrations/__pycache__/0005_alter_generaldocument_category.cpython-313.pyc
drones/migrations/__pycache__/0006_delete_standardoperatingprocedure.cpython-313.pyc
drones/migrations/__pycache__/0007_equipment.cpython-313.pyc
drones/migrations/__pycache__/__init__.cpython-313.pyc
drones/templates/drones/documents.html
drones/templates/drones/equipment_confirm_delete.html
drones/templates/drones/equipment_form.html
drones/templates/drones/equipment_list.html
drones/templates/drones/general_list.html
drones/templates/drones/incident_List.html
drones/templates/drones/incident_report_detail.html
drones/templates/drones/incident_report_form.html
drones/templates/drones/incident_report_pdf.html
drones/templates/drones/incident_report_success.html
drones/templates/drones/incident_reporting_system.html
drones/templates/drones/upload_general.html
drones/templates/drones/wizard_form.html
drones/templates/sop_manager/sop.py
drones/templates/sop_manager/sop_list.html
drones/templates/sop_manager/sop_upload.html
django_drones-0.1.dist-info/METADATA
django_drones-0.1.dist-info/WHEEL
django_drones-0.1.dist-info/top_level.txt
django_drones-0.1.dist-info/RECORD
